[{"directory":"e:\\51_practise\\17_DS18B20\\17_DS18B20","file":"e:\\51_practise\\17_DS18B20\\17_DS18B20\\src\\Com\\Com_util.c","command":"\"d:\\Keill_5\\C51\\BIN\\C51.exe\" .\\src\\Com\\Com_util.c OMF2 TABS(4) CODE NOCOND SYMBOLS INCDIR(d:/Keill_5/C51/INC/STC;src/App;src/Com;src/Dri;src/Int;d:/Keill_5/C51/INC) DEFINE(__UVISION_VERSION='526') OPTIMIZE(8,SPEED) SMALL ROM(LARGE) PRINT(.\\build\\Debug\\.obj\\src\\Com\\Com_util.lst) OBJECT(.\\build\\Debug\\.obj\\src\\Com\\Com_util.o)"},{"directory":"e:\\51_practise\\17_DS18B20\\17_DS18B20","file":"e:\\51_practise\\17_DS18B20\\17_DS18B20\\src\\Dri\\Dri_1_Wire.c","command":"\"d:\\Keill_5\\C51\\BIN\\C51.exe\" .\\src\\Dri\\Dri_1_Wire.c OMF2 TABS(4) CODE NOCOND SYMBOLS INCDIR(d:/Keill_5/C51/INC/STC;src/App;src/Com;src/Dri;src/Int;d:/Keill_5/C51/INC) DEFINE(__UVISION_VERSION='526') OPTIMIZE(8,SPEED) SMALL ROM(LARGE) PRINT(.\\build\\Debug\\.obj\\src\\Dri\\Dri_1_Wire.lst) OBJECT(.\\build\\Debug\\.obj\\src\\Dri\\Dri_1_Wire.o)"},{"directory":"e:\\51_practise\\17_DS18B20\\17_DS18B20","file":"e:\\51_practise\\17_DS18B20\\17_DS18B20\\src\\Dri\\Dri_IIC.c","command":"\"d:\\Keill_5\\C51\\BIN\\C51.exe\" .\\src\\Dri\\Dri_IIC.c OMF2 TABS(4) CODE NOCOND SYMBOLS INCDIR(d:/Keill_5/C51/INC/STC;src/App;src/Com;src/Dri;src/Int;d:/Keill_5/C51/INC) DEFINE(__UVISION_VERSION='526') OPTIMIZE(8,SPEED) SMALL ROM(LARGE) PRINT(.\\build\\Debug\\.obj\\src\\Dri\\Dri_IIC.lst) OBJECT(.\\build\\Debug\\.obj\\src\\Dri\\Dri_IIC.o)"},{"directory":"e:\\51_practise\\17_DS18B20\\17_DS18B20","file":"e:\\51_practise\\17_DS18B20\\17_DS18B20\\src\\Int\\Int_DS18B20.c","command":"\"d:\\Keill_5\\C51\\BIN\\C51.exe\" .\\src\\Int\\Int_DS18B20.c OMF2 TABS(4) CODE NOCOND SYMBOLS INCDIR(d:/Keill_5/C51/INC/STC;src/App;src/Com;src/Dri;src/Int;d:/Keill_5/C51/INC) DEFINE(__UVISION_VERSION='526') OPTIMIZE(8,SPEED) SMALL ROM(LARGE) PRINT(.\\build\\Debug\\.obj\\src\\Int\\Int_DS18B20.lst) OBJECT(.\\build\\Debug\\.obj\\src\\Int\\Int_DS18B20.o)"},{"directory":"e:\\51_practise\\17_DS18B20\\17_DS18B20","file":"e:\\51_practise\\17_DS18B20\\17_DS18B20\\src\\Int\\Int_OLED.c","command":"\"d:\\Keill_5\\C51\\BIN\\C51.exe\" .\\src\\Int\\Int_OLED.c OMF2 TABS(4) CODE NOCOND SYMBOLS INCDIR(d:/Keill_5/C51/INC/STC;src/App;src/Com;src/Dri;src/Int;d:/Keill_5/C51/INC) DEFINE(__UVISION_VERSION='526') OPTIMIZE(8,SPEED) SMALL ROM(LARGE) PRINT(.\\build\\Debug\\.obj\\src\\Int\\Int_OLED.lst) OBJECT(.\\build\\Debug\\.obj\\src\\Int\\Int_OLED.o)"},{"directory":"e:\\51_practise\\17_DS18B20\\17_DS18B20","file":"e:\\51_practise\\17_DS18B20\\17_DS18B20\\src\\main.c","command":"\"d:\\Keill_5\\C51\\BIN\\C51.exe\" .\\src\\main.c OMF2 TABS(4) CODE NOCOND SYMBOLS INCDIR(d:/Keill_5/C51/INC/STC;src/App;src/Com;src/Dri;src/Int;d:/Keill_5/C51/INC) DEFINE(__UVISION_VERSION='526') OPTIMIZE(8,SPEED) SMALL ROM(LARGE) PRINT(.\\build\\Debug\\.obj\\src\\main.lst) OBJECT(.\\build\\Debug\\.obj\\src\\main.o)"}]